pycodesync
