Metadata-Version: 1.0
Name: pycodesync
Version: 0.1.2
Summary: Code sync command line application.
Home-page: UNKNOWN
Author: chenyaofo
Author-email: chenyaofo@gmail.com
License: UNKNOWN
Platform: UNKNOWN
